.VERSION
AUTHORS.rst
CONTRIBUTING.rst
HISTORY.rst
LICENSE
MANIFEST.in
Pipfile
Pipfile.lock
README.rst
USAGE.rst
dev-requirements.txt
requirements.txt
setup.cfg
setup.py
docs/Makefile
docs/authors.rst
docs/conf.py
docs/contributing.rst
docs/history.rst
docs/index.rst
docs/installation.rst
docs/readme.rst
docs/usage.rst
oktauilib/.VERSION
oktauilib/AUTHORS.rst
oktauilib/CONTRIBUTING.rst
oktauilib/HISTORY.rst
oktauilib/LICENSE
oktauilib/Pipfile
oktauilib/Pipfile.lock
oktauilib/README.rst
oktauilib/USAGE.rst
oktauilib/__init__.py
oktauilib/_version.py
oktauilib/authentication.py
oktauilib/dev-requirements.txt
oktauilib/models.py
oktauilib/oktauilib.py
oktauilib/oktauilibexceptions.py
oktauilib/requirements.txt
oktauilib.egg-info/PKG-INFO
oktauilib.egg-info/SOURCES.txt
oktauilib.egg-info/dependency_links.txt
oktauilib.egg-info/not-zip-safe
oktauilib.egg-info/requires.txt
oktauilib.egg-info/top_level.txt
oktauilib/__pycache__/__init__.cpython-37.pyc
oktauilib/__pycache__/__init__.cpython-39.pyc
oktauilib/__pycache__/_version.cpython-37.pyc
oktauilib/__pycache__/_version.cpython-39.pyc
oktauilib/__pycache__/authentication.cpython-37.pyc
oktauilib/__pycache__/authentication.cpython-39.pyc
oktauilib/__pycache__/models.cpython-37.pyc
oktauilib/__pycache__/models.cpython-39.pyc
oktauilib/__pycache__/oktauilib.cpython-37.pyc
oktauilib/__pycache__/oktauilib.cpython-39.pyc
oktauilib/__pycache__/oktauilibexceptions.cpython-37.pyc
oktauilib/__pycache__/oktauilibexceptions.cpython-39.pyc