Metadata-Version: 2.1
Name: oktauilib
Version: 0.2.1
Summary: Library to interact with Okta via UI
Home-page: https://github.com/schubergphilis/oktauilib
Author: Costas Tyfoxylos
Author-email: ctyfoxylos@schubergphilis.com
License: MIT
Keywords: oktauilib
Platform: UNKNOWN
Classifier: Development Status :: 5 - Production/Stable
Classifier: Intended Audience :: Developers
Classifier: License :: OSI Approved :: MIT License
Classifier: Natural Language :: English
Classifier: Programming Language :: Python :: 3.7
